Metadata-Version: 2.1
Name: girlfriendpy
Version: 0.2
Summary: i think i have a gf i dont entirely know how a gf is defined but i think she is so i made this library to help me
